emass_client/__init__.py
emass_client/api_client.py
emass_client/api_response.py
emass_client/configuration.py
emass_client/exceptions.py
emass_client/py.typed
emass_client/rest.py
emass_client/api/__init__.py
emass_client/api/artifacts_api.py
emass_client/api/artifacts_export_api.py
emass_client/api/cac_api.py
emass_client/api/cloud_resource_results_api.py
emass_client/api/cmmc_assessment_dashboards_api.py
emass_client/api/cmmc_assessments_api.py
emass_client/api/coast_guard_system_fisma_metrics_dashboard_api.py
emass_client/api/container_scan_results_api.py
emass_client/api/controls_api.py
emass_client/api/device_scan_results_api.py
emass_client/api/hardware_baseline_api.py
emass_client/api/milestones_api.py
emass_client/api/organization_migration_status_dashboard_api.py
emass_client/api/pac_api.py
emass_client/api/poam_api.py
emass_client/api/registration_api.py
emass_client/api/software_baseline_api.py
emass_client/api/static_code_scans_api.py
emass_client/api/system_application_findings_dashboards_api.py
emass_client/api/system_artifacts_dashboards_api.py
emass_client/api/system_associations_dashboard_api.py
emass_client/api/system_atciatc_dashboard_api.py
emass_client/api/system_conmon_integration_status_dashboard_api.py
emass_client/api/system_connectivity_ccsd_dashboards_api.py
emass_client/api/system_critical_assets_dashboard_api.py
emass_client/api/system_device_findings_dashboards_api.py
emass_client/api/system_fisma_metrics_dashboard_api.py
emass_client/api/system_hardware_dashboards_api.py
emass_client/api/system_migration_status_dashboard_api.py
emass_client/api/system_poam_dashboards_api.py
emass_client/api/system_ports_protocols_dashboards_api.py
emass_client/api/system_privacy_dashboard_api.py
emass_client/api/system_questionnaire_dashboards_api.py
emass_client/api/system_roles_api.py
emass_client/api/system_security_controls_dashboards_api.py
emass_client/api/system_sensor_hardware_dashboards_api.py
emass_client_api-3.22.0.dist-info/METADATA
emass_client_api-3.22.0.dist-info/WHEEL
emass_client_api-3.22.0.dist-info/top_level.txt
emass_client_api-3.22.0.dist-info/RECORD
